{"framework":"apd-framework-9.0.12","title":"Nápověda pro Safari","build_id":"55d777d60946220575c5d878","icon":"..\/GlobalArt\/AppIconDefault_Safari.png","sections":{"ibrwc2a4c26f":{"name":"Vlastní nastavení Safari","children":["ibrw1020","ibrw1012","ibrwa008","ibrw1068","sfri32508","ibrw1015"]},"ibrw8586170f":{"name":"Soukromí a zabezpečení","children":["sfri11471","sfri40696","sfri47acf5d6","ibrw1069","sfri40697","sfri40732"]},"ibrwdcc86085":{"name":"Procházení webu","children":["ibrw1005","sfrid73436cb","sfri40726","sfri22092","ibrw1039","sfri11576","ibrwae910b47","ibrw1103"]},"ibrwf52aedab":{"name":"Čtení článků a sdílených odkazů","children":["sfri35905","sfri32632","sfri1ab55c18","sfri01321aaa"]},"ibrwcd7d7c47":{"name":"Stahování, sdílení a ukládání obsahu","children":["sfri40598","sfri40722","sfri40785","ibrw1089","ibrw1060"]}},"birdseed_version":4,"toc":["sfri35862","ibrwdcc86085","ibrwf52aedab","ibrwcd7d7c47","ibrwc2a4c26f","ibrw8586170f","cpsh003","sfri11861"],"locale":"cs","version":"9.0","enable_tracking":false,"source_schema":"apd-schema","platform":"mac","build_date":"2015.08.21-12:18:47","landing":"sfri35476","product":"safari","urls":{},"copyright":"","topics":{"ibrw1066":{"searchName":"Informace o certifikátech a šifrovaných webových stránkách v Safari","unavailable":true,"name":"Informace o certifikátech a šifrovaných webových stránkách","href":"ibrw1066.html"},"sfri5bcd1b2e":{"categories":["glossary"],"name":"malware","href":"sfri5bcd1b2e.html","unavailable":true},"sfri32508":{"name":"Použití rozšíření Safari","href":"sfri32508.html","unavailable":true},"sfri563ecfdc":{"categories":["glossary"],"name":"Návrhy Spotlightu","href":"sfri563ecfdc.html","unavailable":true},"ibrw1074":{"name":"Panel Zabezpečení v předvolbách Safari","href":"ibrw1074.html","unavailable":true},"ibrw1075":{"name":"Panel Pokročilé v předvolbách Safari","href":"ibrw1075.html","unavailable":true},"sfri27594":{"searchName":"Co dělat, když potřebujete odstranit modul plug-in v Safari","unavailable":true,"name":"Co dělat, když potřebujete odstranit modul plug-in","href":"sfri27594.html"},"ibrw1068":{"searchName":"Zvětšení webové stránky v Safari","unavailable":true,"name":"Zvětšování na webových stránkách","href":"ibrw1068.html"},"ibrw1069":{"searchName":"Používání oken anonymního procházení v Safari","unavailable":true,"name":"Používání oken anonymního procházení","href":"ibrw1069.html"},"ibrw1090":{"searchName":"Zobrazení PDF souborů v Safari","unavailable":true,"name":"Zobrazení PDF souborů","href":"ibrw1090.html"},"sfri11861":{"name":"Řešení problémů","href":"sfri11861.html","unavailable":true},"ibrw1077":{"name":"Pokud aplikace Safari nemůže otevřít okno","href":"ibrw1077.html","unavailable":true},"ibrwa001":{"searchName":"Proč na webových stránkách v Safari blokovat vyskakovací okna?","unavailable":true,"name":"Proč blokovat vyskakovací okna?","href":"ibrwa001.html"},"ibrw1080":{"searchName":"Výběr webových stránek, které si mohou uživatelé prohlížet v Safari","unavailable":true,"name":"Výběr webových stránek, které si mohou uživatelé prohlížet","href":"ibrw1080.html"},"ibrw2737362b":{"categories":["glossary"],"name":"Dynamické vyhledávací pole","href":"ibrw2737362b.html","unavailable":true},"sfri43593":{"searchName":"Má-li webová stránka obsah vyžadující plug-in pro Safari","unavailable":true,"name":"Má-li webová stránka obsah vyžadující plug-in","href":"sfri43593.html"},"sfri40598":{"searchName":"Stahování položek z webových stránek pomocí Safari","unavailable":true,"name":"Stahování položek z webu","href":"sfri40598.html"},"ibrwa005":{"name":"Panel automatického vyplňování v předvolbách Safari","href":"ibrwa005.html","unavailable":true},"sfri01321aaa":{"searchName":"Odběr článků z webových stránek pomocí Safari","unavailable":true,"name":"Odběr článků","href":"sfri01321aaa.html"},"sfri40599":{"name":"Panel Hesla v předvolbách Safari","href":"sfri40599.html","unavailable":true},"ibrwe75c2a3c":{"searchName":"Změna voleb hledání pomocí Safari","unavailable":true,"name":"Změna voleb hledání","href":"ibrwe75c2a3c.html"},"ibrwa006":{"name":"Co dělat, když Safari nemůže stáhnout položku z webu","href":"ibrwa006.html","unavailable":true},"ibrwa007":{"name":"Co se stane, pokusíte-li se použít Safari v době, kdy jste offline","href":"ibrwa007.html"},"ibrw1089":{"searchName":"Ukládání webových stránek pomocí Safari","unavailable":true,"name":"Ukládání webových stránek","href":"ibrw1089.html"},"ibrwa008":{"name":"Nastavení Safari jako výchozího webového prohlížeče","href":"ibrwa008.html","unavailable":true},"sfrid73436cb":{"searchName":"Nalezení hledaných stránek v Safari","unavailable":true,"name":"Nalezení hledaných stránek","href":"sfrid73436cb.html"},"ibrwae910b47":{"name":"Vypnutí zvuku na kartách","href":"ibrwae910b47.html","unavailable":true},"sfri11576":{"searchName":"Zobrazení webových stránek na panelech v Safari","unavailable":true,"name":"Zobrazení webových stránek na panelech","href":"sfri11576.html"},"sfri1ab55c18":{"searchName":"Zobrazení sdílených odkazů a kanálů v Safari","unavailable":true,"name":"Zobrazení sdílených odkazů a kanálů","href":"sfri1ab55c18.html"},"sfri35610":{"name":"Panel Soukromí v předvolbách Safari","href":"sfri35610.html","unavailable":true},"cpsh003":{"name":"Klávesové a další zkratky","href":"cpsh003.html","unavailable":true},"sfri40696":{"searchName":"Blokování vyskakovacích oken a nevyžádaného obsahu v Safari","unavailable":true,"name":"Blokování vyskakovacích oken a nevyžádaného obsahu","href":"sfri40696.html"},"sfri35826":{"name":"Použití vašeho internetového účtu s jinými aplikacemi pro systém OS X","href":"sfri35826.html","unavailable":true},"sfri40697":{"searchName":"Identifikace šifrovaných webových stránek a ochrana před podvodnými stránkami v Safari","unavailable":true,"name":"Identifikace šifrovaných webových stránek a ochrana před podvodnými stránkami","href":"sfri40697.html"},"sfri32632":{"searchName":"Čtení článků bez rušivých prvků v Čtečce Safari","unavailable":true,"name":"Čtení článků bez rušivých prvků","href":"sfri32632.html"},"sfri4b415f9c":{"searchName":"Webová stránka s grafikou WebGL v Safari","unavailable":true,"name":"Webová stránka s grafikou WebGL","href":"sfri4b415f9c.html"},"sfri35905":{"searchName":"Udržování seznamu četby v Safari","unavailable":true,"name":"Udržování seznamu četby","href":"sfri35905.html"},"ibrw1005":{"searchName":"Otvírání webových stránek v Safari","unavailable":true,"name":"Otvírání webových stránek","href":"ibrw1005.html"},"ibrw1012":{"name":"Přizpůsobení okna Safari","href":"ibrw1012.html","unavailable":true},"ibrw1020":{"searchName":"Nastavení domovské stránky v Safari","unavailable":true,"name":"Nastavení domovské stránky","href":"ibrw1020.html"},"ibrw1006":{"searchName":"Návštěva webových stránek Bonjour v Safari","unavailable":true,"name":"Návštěva webových stránek Bonjour","href":"ibrw1006.html"},"sfri20948":{"name":"Použití nabídky Vývojář v Safari","href":"sfri20948.html","unavailable":true},"sfri35476":{"icon":"..\/GlobalArt\/AppLanding_Safari.png","categories":["landing"],"name":"Nápověda pro Safari","href":"sfri35476.html"},"sfria1042d31":{"name":"Panel Hledat v předvolbách Safari","href":"sfria1042d31.html","unavailable":true},"ibrw1015":{"searchName":"Import záložek a historie do Safari z jiných prohlížečů","unavailable":true,"name":"Import záložek a historie","href":"ibrw1015.html"},"sfri40785":{"searchName":"Přidání lístků do Passbooku v Safari","unavailable":true,"name":"Přidání lístků do Walletu","href":"sfri40785.html"},"sfri20879":{"searchName":"Databáze uložené v počítači pomocí Safari","unavailable":true,"name":"Databáze uložené v počítači","href":"sfri20879.html"},"ibrw1009":{"searchName":"Opakované návštěvy webových stránek prostřednictvím historie aplikace Safari","unavailable":true,"name":"Opakované návštěvy webových stránek","href":"ibrw1009.html"},"ibrw1100":{"searchName":"Co dělat, když v Safari nefunguje automatické vyplňování","unavailable":true,"name":"Co dělat, když nefunguje automatické vyplňování","href":"ibrw1100.html"},"sfri35922":{"name":"Co dělat, když v Safari dojde k chybě při zobrazování webové stránky","href":"sfri35922.html","unavailable":true},"sfri4f24ca1c":{"name":"Co dělat, pokud Safari zobrazí bezpečnostní upozornění na WebGL","href":"sfri4f24ca1c.html","unavailable":true},"ibrw1031":{"searchName":"Co dělat, když se webová stránka nezobrazí v Safari správně","unavailable":true,"name":"Co dělat, když se webová stránka nezobrazí správně","href":"ibrw1031.html"},"sfri21978704":{"categories":["glossary"],"name":"cookies a data webových stránek","href":"sfri21978704.html","unavailable":true},"ibrw1018":{"searchName":"Zkoumání prvků a aktivity webové stránky v Safari","unavailable":true,"name":"Zkoumání prvků a aktivity webové stránky","href":"ibrw1018.html"},"ibrw1032":{"searchName":"Pokud v Safari nefungují funkce na dané webové stránce","unavailable":true,"name":"Pokud nefungují funkce na dané webové stránce","href":"ibrw1032.html"},"ibrw1103":{"searchName":"Automatické vyplňování webových formulářů v Safari","unavailable":true,"name":"Použití automatického vyplňování","href":"ibrw1103.html"},"ibrw1033":{"name":"Co dělat, když Safari nezobrazuje obrázky na webové stránce","href":"ibrw1033.html","unavailable":true},"ibrw1041":{"searchName":"Co dělat, když v řádku záložek aplikace Safari chybí řádek oblíbených položek","unavailable":true,"name":"Co dělat, když v řádku oblíbených položek chybí záložky","href":"ibrw1041.html"},"sfri35862":{"name":"Přehled Safari","href":"sfri35862.html","unavailable":true},"sfri264b84ab":{"categories":["glossary"],"name":"přitlačení","href":"sfri264b84ab.html","unavailable":true},"sfri11471":{"searchName":"Správa cookies a dat webových stránek v Safari","unavailable":true,"name":"Správa cookies a dat webových stránek","href":"sfri11471.html"},"ibrw1113":{"searchName":"Jak vylepšit vyhledávání na webu v aplikaci Safari","unavailable":true,"name":"Jak vylepšit vyhledávání na webu","href":"ibrw1113.html"},"sfri47acf5d6":{"searchName":"Vymazání historie prohlížení v Safari","unavailable":true,"name":"Vymazání historie prohlížení","href":"sfri47acf5d6.html"},"ibrw1036":{"searchName":"Co dělat, když v Safari chybí modul plug-in","unavailable":true,"name":"Co dělat, když chybí modul plug-in","href":"ibrw1036.html"},"ibrw1114":{"searchName":"Hledání v historii prohlížení webu aplikace Safari","unavailable":true,"name":"Hledání v historii prohlížení","href":"ibrw1114.html"},"sfri40722":{"searchName":"Sdílení, tweetování a zveřejňování webových stránek v Safari","unavailable":true,"name":"Sdílení, tweetování a zveřejňování stránek","href":"sfri40722.html"},"ibrw1045":{"name":"Panely v předvolbách Safari","href":"ibrw1045.html","unavailable":true},"ibrw1053":{"searchName":"Nastavení proxy serveru v aplikaci Safari","unavailable":true,"name":"Nastavení proxy serveru","href":"ibrw1053.html"},"ibrw1039":{"searchName":"Používání záložek v Safari","unavailable":true,"name":"Používání záložek","href":"ibrw1039.html"},"ibrw1060":{"searchName":"Tisk webových stránek ze Safari","unavailable":true,"name":"Tisk webových stránek","href":"ibrw1060.html"},"ibrw1117":{"name":"Co dělat, když Safari nemůže uložit heslo","href":"ibrw1117.html","unavailable":true},"sfri22092":{"searchName":"Zobrazení stránky Oblíbené a Top Sites v Safari","unavailable":true,"name":"Zobrazení oblíbených položek a Top Sites","href":"sfri22092.html"},"sfri40724":{"name":"Panel Oznámení v předvolbách Safari","href":"sfri40724.html","unavailable":true},"ibrw1118":{"name":"Co dělat, když jsou některé funkce Safari nedostupné nebo se zobrazí výzva k zadání hesla","href":"ibrw1118.html","unavailable":true},"sfri40732":{"searchName":"Požádání webových stránek, aby vás v Safari nesledovaly","unavailable":true,"name":"Požádání webových stránek, aby vás nesledovaly","href":"sfri40732.html"},"sfri78488bc1":{"categories":["glossary"],"name":"správce","href":"sfri78488bc1.html","unavailable":true},"sfri40726":{"searchName":"Zobrazení otevřených webových stránek na jiných zařízeních v prohlížeči Safari","unavailable":true,"name":"Zobrazení otevřených webových stránek na jiných zařízeních","href":"sfri40726.html"},"ibrw1071":{"name":"Co dělat, když Safari nemůže otevřít webovou stránku","href":"ibrw1071.html","unavailable":true},"ibrw1072":{"name":"Panel Obecné v předvolbách Safari","href":"ibrw1072.html","unavailable":true},"sfri21236":{"searchName":"Co dělat, když se šifrovaná webová stránka v Safari neotvírá","unavailable":true,"name":"Co dělat, když se šifrovaná webová stránka neotvírá","href":"sfri21236.html"},"sfri40734":{"searchName":"Správa oznámení webových stránek v Safari","unavailable":true,"name":"Spravování oznámení webových stránek","href":"sfri40734.html"},"sfri32153":{"name":"Panel Rozšíření v předvolbách Safari","href":"sfri32153.html","unavailable":true}},"copyright_text":"© 2015 Apple Inc. Všechna práva vyhrazena.","css":""}